{"shops":{"Flash_Deals":{"flash_deal_ingredient":{},"flash_deal_generator":{},"flash_deal_material":{},"flash_deal_chest":{},"flash_deal_key":{},"flash_deal_greenhouse":{}},"Crates":{"crates_10_rv":{},"crates_10_no_ads":{},"crates_30":{},"crates_90":{},"crates_200":{},"crates_375":{},"crates_1000":{}},"Energy":{"energy_5_rv":{},"energy_5_no_ads":{},"energy_80":{},"energy_300":{},"energy_500":{},"energy_800":{},"energy_2000":{}},"Gems":{"gems_3500":{},"gems_5_rv":{},"gems_5_no_ads":{},"gems_200":{},"gems_900":{}},"Halloween":{"halloween_001_pack":{},"halloween_001_hauntedhouse":{},"halloween_001_grandfatherclock":{},"halloween_001_ghosts":{},"halloween_001_grave01":{},"halloween_001_grave02":{},"halloween_001_well":{},"halloween_002_pack":{},"halloween_002_cauldron":{},"halloween_002_blackcat":{},"halloween_003_pack":{},"halloween_003_skeletoncarousel":{},"halloween_003_skeletonbench":{},"halloween_003_skeletonpicnic":{},"halloween_003_skullaltar":{},"halloween_004_pack":{},"halloween_004_pumpkinpatchbig":{},"halloween_004_pumpkins01":{},"halloween_004_pumpkins02":{},"halloween_004_pumpkins03":{},"halloween_004_pumpkins04":{}},"Christmas":{"christmas_001_pack":{},"christmas_001_snowjello":{},"christmas_001_snowfight":{},"christmas_001_snowdinner":{},"christmas_001_snowgifting":{},"christmas_001_snowreindeer":{},"christmas_001_snowglobe":{},"christmas_001_snowtelescope":{},"christmas_002_pack":{},"christmas_002_fireplace":{},"christmas_002_gift02":{},"christmas_002_nutcracker":{},"christmas_002_snowlantern":{},"christmas_003_pack":{},"christmas_003_candygate":{},"christmas_003_gingerbell":{},"christmas_003_gingerbreadsnow":{},"christmas_003_gingerbreadhouse":{},"christmas_003_gingerbreadhousesmall":{},"christmas_004_pack":{},"christmas_004_gift01":{},"christmas_004_elfteddy":{},"christmas_004_santamail":{},"christmas_004_gift03":{},"christmas_004_santagift":{},"christmas_004_elftrain":{},"christmas_004_elfmail":{}},"BlackFriday":{"black_friday_001":{},"black_friday_002":{},"black_friday_003":{},"black_friday_004":{}},"ChristmasDeals":{"christmas_deals_001":{},"christmas_deals_002":{},"christmas_deals_003":{},"christmas_deals_004":{}}}}